.DS_Store
cs207_g7-1.1.5.dist-info/DESCRIPTION.rst
cs207_g7-1.1.5.dist-info/METADATA
cs207_g7-1.1.5.dist-info/RECORD
cs207_g7-1.1.5.dist-info/WHEEL
cs207_g7-1.1.5.dist-info/metadata.json
cs207_g7-1.1.5.dist-info/top_level.txt
kinetics/.DS_Store
kinetics/.coverage
kinetics/__init__.py
kinetics/chemkin.py
kinetics/history.py
kinetics/nasa.py
kinetics/__pycache__/__init__.cpython-36.pyc
kinetics/__pycache__/chemkin.cpython-36.pyc
kinetics/__pycache__/history.cpython-36.pyc
kinetics/__pycache__/nasa.cpython-36.pyc
kinetics/data/NASA.sqlite
kinetics/test/.DS_Store
kinetics/test/test_NASA_coeff.py
kinetics/test/test_XML_reader.py
kinetics/test/test_backward_reaction_rate_coeff.py
kinetics/test/test_history_reader.py
kinetics/test/test_reaction.py
kinetics/test/test_reaction_coeff.py
kinetics/test/test_reaction_component_coefficients.py
kinetics/test/__pycache__/test_NASA_coeff.cpython-36-PYTEST.pyc
kinetics/test/__pycache__/test_XML_reader.cpython-36-PYTEST.pyc
kinetics/test/__pycache__/test_backward_reaction_rate_coeff.cpython-36-PYTEST.pyc
kinetics/test/__pycache__/test_history_reader.cpython-36-PYTEST.pyc
kinetics/test/__pycache__/test_reaction.cpython-36-PYTEST.pyc
kinetics/test/__pycache__/test_reaction_coeff.cpython-36-PYTEST.pyc
kinetics/test/__pycache__/test_reaction_component_coefficients.cpython-36-PYTEST.pyc
kinetics/test/xml/rxns_reversible.xml
kinetics/test/xml/xml_bad_products.xml
kinetics/test/xml/xml_bad_reactants.xml
kinetics/test/xml/xml_good1.xml
kinetics/test/xml/xml_good2.xml
kinetics/test/xml/xml_homework.xml
kinetics/test/xml/xml_reversible_and_irreversible.xml
