Metadata-Version: 2.0
Name: cs207-g7
Version: 1.1.5
Summary: A simple chemical kinetics library
Home-page: https://github.com/CS207G7/cs207-FinalProject
Author: CS207 Group 7
Author-email: benrafetto@gmail.com
License: MIT
Platform: UNKNOWN
Classifier: Development Status :: 3 - Alpha
Classifier: Intended Audience :: Developers
Classifier: Topic :: Software Development :: Build Tools
Classifier: License :: OSI Approved :: MIT License
Classifier: Programming Language :: Python :: 3
Classifier: Programming Language :: Python :: 3.3
Classifier: Programming Language :: Python :: 3.4
Classifier: Programming Language :: Python :: 3.5
Requires-Dist: pymysql
